{
"meta":{"test_sets":[],"test_metrics":[],"learn_metrics":[{"best_value":"Min","name":"RMSE"}],"launch_mode":"Train","parameters":"","iteration_count":300,"learn_sets":["learn"],"name":"experiment"},
"iterations":[
{"learn":[11600.20363],"iteration":0,"passed_time":0.001576913273,"remaining_time":0.4714970687},
{"learn":[11207.31686],"iteration":1,"passed_time":0.002672687017,"remaining_time":0.3982303656},
{"learn":[10814.8291],"iteration":2,"passed_time":0.003675634537,"remaining_time":0.3638878192},
{"learn":[10471.78639],"iteration":3,"passed_time":0.004557648607,"remaining_time":0.3372659969},
{"learn":[10115.37753],"iteration":4,"passed_time":0.005411052024,"remaining_time":0.3192520694},
{"learn":[9782.230752],"iteration":5,"passed_time":0.006194355417,"remaining_time":0.3035234154},
{"learn":[9460.403354],"iteration":6,"passed_time":0.006998702556,"remaining_time":0.2929456927},
{"learn":[9163.689096],"iteration":7,"passed_time":0.007769535619,"remaining_time":0.2835880501},
{"learn":[8846.090835],"iteration":8,"passed_time":0.008563260165,"remaining_time":0.2768787453},
{"learn":[8572.234293],"iteration":9,"passed_time":0.009357366586,"remaining_time":0.271363631},
{"learn":[8313.449093],"iteration":10,"passed_time":0.01013572282,"remaining_time":0.2662930815},
{"learn":[8056.97095],"iteration":11,"passed_time":0.01109476989,"remaining_time":0.2662744774},
{"learn":[7822.494053],"iteration":12,"passed_time":0.01207720085,"remaining_time":0.2666274342},
{"learn":[7618.931713],"iteration":13,"passed_time":0.01292511856,"remaining_time":0.2640417078},
{"learn":[7427.925356],"iteration":14,"passed_time":0.01379883986,"remaining_time":0.2621779573},
{"learn":[7259.072329],"iteration":15,"passed_time":0.01461051286,"remaining_time":0.2593366033},
{"learn":[7066.772163],"iteration":16,"passed_time":0.01537572868,"remaining_time":0.2559606598},
{"learn":[6910.728075],"iteration":17,"passed_time":0.01612912807,"remaining_time":0.2526896731},
{"learn":[6747.330365],"iteration":18,"passed_time":0.01687236216,"remaining_time":0.2495333561},
{"learn":[6584.511392],"iteration":19,"passed_time":0.01760811956,"remaining_time":0.2465136738},
{"learn":[6437.495239],"iteration":20,"passed_time":0.01841575894,"remaining_time":0.2446665117},
{"learn":[6298.596373],"iteration":21,"passed_time":0.01918262829,"remaining_time":0.2423986666},
{"learn":[6163.114993],"iteration":22,"passed_time":0.01996003036,"remaining_time":0.2403881917},
{"learn":[6046.984458],"iteration":23,"passed_time":0.02073215815,"remaining_time":0.2384198187},
{"learn":[5933.876048],"iteration":24,"passed_time":0.02148312132,"remaining_time":0.2363143345},
{"learn":[5828.593421],"iteration":25,"passed_time":0.02224646771,"remaining_time":0.2344435443},
{"learn":[5720.535208],"iteration":26,"passed_time":0.02306227144,"remaining_time":0.233185189},
{"learn":[5628.788516],"iteration":27,"passed_time":0.02343696293,"remaining_time":0.2276733542},
{"learn":[5553.262487],"iteration":28,"passed_time":0.02417975144,"remaining_time":0.2259556083},
{"learn":[5478.580425],"iteration":29,"passed_time":0.02493459397,"remaining_time":0.2244113457},
{"learn":[5397.201108],"iteration":30,"passed_time":0.02569394117,"remaining_time":0.2229571025},
{"learn":[5322.596192],"iteration":31,"passed_time":0.02646017142,"remaining_time":0.2216039357},
{"learn":[5257.37347],"iteration":32,"passed_time":0.02722057369,"remaining_time":0.2202391871},
{"learn":[5196.082445],"iteration":33,"passed_time":0.02807711578,"remaining_time":0.2196621411},
{"learn":[5133.781469],"iteration":34,"passed_time":0.02893579245,"remaining_time":0.2190852857},
{"learn":[5073.772098],"iteration":35,"passed_time":0.02939696567,"remaining_time":0.2155777483},
{"learn":[5021.708453],"iteration":36,"passed_time":0.03020314471,"remaining_time":0.2146872178},
{"learn":[4985.851124],"iteration":37,"passed_time":0.03037957879,"remaining_time":0.2094592011},
{"learn":[4933.321047],"iteration":38,"passed_time":0.03117173589,"remaining_time":0.2086108479},
{"learn":[4886.19219],"iteration":39,"passed_time":0.03194591802,"remaining_time":0.2076484671},
{"learn":[4844.504589],"iteration":40,"passed_time":0.03231413039,"remaining_time":0.2041307261},
{"learn":[4803.837379],"iteration":41,"passed_time":0.03307849637,"remaining_time":0.2031964777},
{"learn":[4766.422259],"iteration":42,"passed_time":0.03383159033,"remaining_time":0.2022027608},
{"learn":[4731.172433],"iteration":43,"passed_time":0.03419513756,"remaining_time":0.1989535276},
{"learn":[4697.963568],"iteration":44,"passed_time":0.0349812401,"remaining_time":0.1982270273},
{"learn":[4673.214973],"iteration":45,"passed_time":0.03520516681,"remaining_time":0.1943937472},
{"learn":[4642.86164],"iteration":46,"passed_time":0.03599820301,"remaining_time":0.1937775609},
{"learn":[4615.351774],"iteration":47,"passed_time":0.0367545059,"remaining_time":0.192961156},
{"learn":[4588.083367],"iteration":48,"passed_time":0.03750612367,"remaining_time":0.1921232049},
{"learn":[4562.086894],"iteration":49,"passed_time":0.03826808718,"remaining_time":0.1913404359},
{"learn":[4537.687059],"iteration":50,"passed_time":0.03904630602,"remaining_time":0.1906378471},
{"learn":[4513.254159],"iteration":51,"passed_time":0.03981247636,"remaining_time":0.1898748872},
{"learn":[4490.620067],"iteration":52,"passed_time":0.04056408552,"remaining_time":0.1890439457},
{"learn":[4471.87558],"iteration":53,"passed_time":0.04130453801,"remaining_time":0.1881651176},
{"learn":[4453.398141],"iteration":54,"passed_time":0.04206345513,"remaining_time":0.1873735729},
{"learn":[4437.16584],"iteration":55,"passed_time":0.04294681041,"remaining_time":0.1871253882},
{"learn":[4429.114035],"iteration":56,"passed_time":0.04314320219,"remaining_time":0.183926283},
{"learn":[4412.069823],"iteration":57,"passed_time":0.04365445886,"remaining_time":0.1821444663},
{"learn":[4394.070911],"iteration":58,"passed_time":0.04442938133,"remaining_time":0.1814827271},
{"learn":[4376.149941],"iteration":59,"passed_time":0.04519067785,"remaining_time":0.1807627114},
{"learn":[4362.281859],"iteration":60,"passed_time":0.04594185865,"remaining_time":0.1800017085},
{"learn":[4351.216846],"iteration":61,"passed_time":0.04668994003,"remaining_time":0.1792291246},
{"learn":[4338.790628],"iteration":62,"passed_time":0.04744666577,"remaining_time":0.1784898379},
{"learn":[4325.054294],"iteration":63,"passed_time":0.0482143784,"remaining_time":0.1777905204},
{"learn":[4314.21251],"iteration":64,"passed_time":0.04895524996,"remaining_time":0.1769920576},
{"learn":[4303.487598],"iteration":65,"passed_time":0.04971347289,"remaining_time":0.1762568584},
{"learn":[4293.908437],"iteration":66,"passed_time":0.05044497182,"remaining_time":0.1754280363},
{"learn":[4282.225132],"iteration":67,"passed_time":0.05122992151,"remaining_time":0.1747844381},
{"learn":[4270.734348],"iteration":68,"passed_time":0.05200835074,"remaining_time":0.1741149134},
{"learn":[4260.999819],"iteration":69,"passed_time":0.05279877237,"remaining_time":0.1734816806},
{"learn":[4249.102488],"iteration":70,"passed_time":0.05355203161,"remaining_time":0.1727241583},
{"learn":[4241.45412],"iteration":71,"passed_time":0.05430158815,"remaining_time":0.1719550292},
{"learn":[4227.151049],"iteration":72,"passed_time":0.05505546067,"remaining_time":0.1711998572},
{"learn":[4217.510102],"iteration":73,"passed_time":0.05580685944,"remaining_time":0.1704371653},
{"learn":[4209.444778],"iteration":74,"passed_time":0.05655103082,"remaining_time":0.1696530925},
{"learn":[4201.963964],"iteration":75,"passed_time":0.05734075687,"remaining_time":0.1690043361},
{"learn":[4190.275801],"iteration":76,"passed_time":0.05813865381,"remaining_time":0.1683755818},
{"learn":[4179.562264],"iteration":77,"passed_time":0.05901059658,"remaining_time":0.1679532364},
{"learn":[4170.104451],"iteration":78,"passed_time":0.05984219766,"remaining_time":0.1674066542},
{"learn":[4162.278995],"iteration":79,"passed_time":0.06070202133,"remaining_time":0.1669305587},
{"learn":[4153.772265],"iteration":80,"passed_time":0.06147506954,"remaining_time":0.1662103732},
{"learn":[4147.058512],"iteration":81,"passed_time":0.06223611366,"remaining_time":0.1654569851},
{"learn":[4141.557853],"iteration":82,"passed_time":0.06300772734,"remaining_time":0.1647310462},
{"learn":[4137.873416],"iteration":83,"passed_time":0.0637688517,"remaining_time":0.1639770472},
{"learn":[4129.027098],"iteration":84,"passed_time":0.06453221048,"remaining_time":0.1632285324},
{"learn":[4123.991793],"iteration":85,"passed_time":0.06530651761,"remaining_time":0.1625069159},
{"learn":[4118.493716],"iteration":86,"passed_time":0.06608038225,"remaining_time":0.1617830048},
{"learn":[4110.092148],"iteration":87,"passed_time":0.06685547551,"remaining_time":0.1610609183},
{"learn":[4104.242192],"iteration":88,"passed_time":0.06761264372,"remaining_time":0.1602951441},
{"learn":[4097.458803],"iteration":89,"passed_time":0.06840226509,"remaining_time":0.1596052852},
{"learn":[4089.491188],"iteration":90,"passed_time":0.06914923907,"remaining_time":0.1588152853},
{"learn":[4080.481781],"iteration":91,"passed_time":0.06992715076,"remaining_time":0.1580961669},
{"learn":[4074.818771],"iteration":92,"passed_time":0.07066346358,"remaining_time":0.1572831931},
{"learn":[4069.492658],"iteration":93,"passed_time":0.07140719869,"remaining_time":0.1564881163},
{"learn":[4067.053217],"iteration":94,"passed_time":0.07217225335,"remaining_time":0.1557401257},
{"learn":[4062.780785],"iteration":95,"passed_time":0.07304767638,"remaining_time":0.1552263123},
{"learn":[4056.985735],"iteration":96,"passed_time":0.07392811991,"remaining_time":0.1547155499},
{"learn":[4053.296558],"iteration":97,"passed_time":0.07483606083,"remaining_time":0.1542539213},
{"learn":[4050.655208],"iteration":98,"passed_time":0.07571674161,"remaining_time":0.1537279299},
{"learn":[4045.169723],"iteration":99,"passed_time":0.07658991093,"remaining_time":0.1531798219},
{"learn":[4041.55543],"iteration":100,"passed_time":0.07740433109,"remaining_time":0.1525095236},
{"learn":[4033.761176],"iteration":101,"passed_time":0.07818293387,"remaining_time":0.1517668716},
{"learn":[4025.735739],"iteration":102,"passed_time":0.07895728542,"remaining_time":0.1510153906},
{"learn":[4024.531191],"iteration":103,"passed_time":0.0792411582,"remaining_time":0.1493391058},
{"learn":[4018.540361],"iteration":104,"passed_time":0.08003909095,"remaining_time":0.148644026},
{"learn":[4014.574549],"iteration":105,"passed_time":0.08082314087,"remaining_time":0.1479215974},
{"learn":[4010.240047],"iteration":106,"passed_time":0.08163788541,"remaining_time":0.1472533821},
{"learn":[4001.650769],"iteration":107,"passed_time":0.08240132408,"remaining_time":0.1464912428},
{"learn":[3999.344157],"iteration":108,"passed_time":0.0831512167,"remaining_time":0.145705343},
{"learn":[3996.657693],"iteration":109,"passed_time":0.08389508093,"remaining_time":0.1449096852},
{"learn":[3986.431775],"iteration":110,"passed_time":0.08467892252,"remaining_time":0.1441830302},
{"learn":[3979.688021],"iteration":111,"passed_time":0.08546079897,"remaining_time":0.1434520554},
{"learn":[3974.724661],"iteration":112,"passed_time":0.08623574381,"remaining_time":0.1427087088},
{"learn":[3972.215985],"iteration":113,"passed_time":0.08698243784,"remaining_time":0.1419187144},
{"learn":[3968.541846],"iteration":114,"passed_time":0.08773265207,"remaining_time":0.1411351359},
{"learn":[3966.5395],"iteration":115,"passed_time":0.08853343218,"remaining_time":0.1404323407},
{"learn":[3961.430186],"iteration":116,"passed_time":0.08937579256,"remaining_time":0.1397929063},
{"learn":[3955.643807],"iteration":117,"passed_time":0.09025055136,"remaining_time":0.1392000029},
{"learn":[3947.381521],"iteration":118,"passed_time":0.09105218336,"remaining_time":0.138491136},
{"learn":[3946.554828],"iteration":119,"passed_time":0.09138821425,"remaining_time":0.1370823214},
{"learn":[3938.792159],"iteration":120,"passed_time":0.09216520173,"remaining_time":0.1363435629},
{"learn":[3936.393512],"iteration":121,"passed_time":0.09295693598,"remaining_time":0.1356256935},
{"learn":[3931.378055],"iteration":122,"passed_time":0.09372334977,"remaining_time":0.1348701862},
{"learn":[3926.895909],"iteration":123,"passed_time":0.09449086269,"remaining_time":0.1341160632},
{"learn":[3919.798834],"iteration":124,"passed_time":0.09526135141,"remaining_time":0.133365892},
{"learn":[3915.658762],"iteration":125,"passed_time":0.09601433346,"remaining_time":0.1325912224},
{"learn":[3909.073421],"iteration":126,"passed_time":0.09677346924,"remaining_time":0.131825277},
{"learn":[3903.390141],"iteration":127,"passed_time":0.09753021322,"remaining_time":0.131056224},
{"learn":[3898.850223],"iteration":128,"passed_time":0.0983109709,"remaining_time":0.130319194},
{"learn":[3894.438582],"iteration":129,"passed_time":0.09907193616,"remaining_time":0.1295556088},
{"learn":[3891.477685],"iteration":130,"passed_time":0.09983373956,"remaining_time":0.1287931449},
{"learn":[3887.636102],"iteration":131,"passed_time":0.1005784137,"remaining_time":0.1280088901},
{"learn":[3885.913625],"iteration":132,"passed_time":0.1013221205,"remaining_time":0.127224016},
{"learn":[3880.969703],"iteration":133,"passed_time":0.1020904358,"remaining_time":0.1264702413},
{"learn":[3875.218281],"iteration":134,"passed_time":0.1028825667,"remaining_time":0.1257453593},
{"learn":[3871.916914],"iteration":135,"passed_time":0.1036683411,"remaining_time":0.1250118231},
{"learn":[3868.240647],"iteration":136,"passed_time":0.1045375133,"remaining_time":0.1243767494},
{"learn":[3857.687577],"iteration":137,"passed_time":0.1054393656,"remaining_time":0.1237766465},
{"learn":[3852.629754],"iteration":138,"passed_time":0.1062978236,"remaining_time":0.1231219395},
{"learn":[3846.968025],"iteration":139,"passed_time":0.1071776624,"remaining_time":0.1224887571},
{"learn":[3840.883675],"iteration":140,"passed_time":0.107960732,"remaining_time":0.1217429531},
{"learn":[3837.722007],"iteration":141,"passed_time":0.1087131683,"remaining_time":0.1209625394},
{"learn":[3833.196779],"iteration":142,"passed_time":0.1094595387,"remaining_time":0.1201758571},
{"learn":[3826.602077],"iteration":143,"passed_time":0.1102075515,"remaining_time":0.1193915141},
{"learn":[3820.939846],"iteration":144,"passed_time":0.1109795918,"remaining_time":0.1186333568},
{"learn":[3817.062017],"iteration":145,"passed_time":0.1117249178,"remaining_time":0.1178468311},
{"learn":[3813.493017],"iteration":146,"passed_time":0.112460524,"remaining_time":0.1170507495},
{"learn":[3808.098125],"iteration":147,"passed_time":0.1132384956,"remaining_time":0.1162989955},
{"learn":[3804.612867],"iteration":148,"passed_time":0.1139859131,"remaining_time":0.1155159254},
{"learn":[3803.712918],"iteration":149,"passed_time":0.1142706839,"remaining_time":0.1142706839},
{"learn":[3796.221032],"iteration":150,"passed_time":0.1150262341,"remaining_time":0.1135027078},
{"learn":[3792.915002],"iteration":151,"passed_time":0.1157930749,"remaining_time":0.1127458887},
{"learn":[3790.424388],"iteration":152,"passed_time":0.1165304186,"remaining_time":0.1119605983},
{"learn":[3786.681167],"iteration":153,"passed_time":0.1172796133,"remaining_time":0.1111871658},
{"learn":[3781.904359],"iteration":154,"passed_time":0.1180432627,"remaining_time":0.1104275683},
{"learn":[3776.774868],"iteration":155,"passed_time":0.1188157066,"remaining_time":0.1096760368},
{"learn":[3772.092396],"iteration":156,"passed_time":0.1195748851,"remaining_time":0.1089121565},
{"learn":[3767.177864],"iteration":157,"passed_time":0.1203815827,"remaining_time":0.1081910427},
{"learn":[3765.020846],"iteration":158,"passed_time":0.1212384219,"remaining_time":0.1075133176},
{"learn":[3762.972964],"iteration":159,"passed_time":0.1220613422,"remaining_time":0.1068036744},
{"learn":[3758.828029],"iteration":160,"passed_time":0.1228569,"remaining_time":0.1060690006},
{"learn":[3755.837097],"iteration":161,"passed_time":0.1235987867,"remaining_time":0.1052878553},
{"learn":[3753.988747],"iteration":162,"passed_time":0.1243991436,"remaining_time":0.1045563354},
{"learn":[3751.576114],"iteration":163,"passed_time":0.1251512,"remaining_time":0.103783922},
{"learn":[3747.244353],"iteration":164,"passed_time":0.1259359624,"remaining_time":0.1030385147},
{"learn":[3743.24151],"iteration":165,"passed_time":0.1267049732,"remaining_time":0.1022799181},
{"learn":[3739.355364],"iteration":166,"passed_time":0.1274528421,"remaining_time":0.1015043593},
{"learn":[3736.503549],"iteration":167,"passed_time":0.1282542118,"remaining_time":0.1007711664},
{"learn":[3732.443932],"iteration":168,"passed_time":0.1290478051,"remaining_time":0.1000311389},
{"learn":[3730.6289],"iteration":169,"passed_time":0.1298295703,"remaining_time":0.09928143613},
{"learn":[3725.937458],"iteration":170,"passed_time":0.1305967651,"remaining_time":0.09852036663},
{"learn":[3720.144174],"iteration":171,"passed_time":0.131340694,"remaining_time":0.09774191184},
{"learn":[3714.912885],"iteration":172,"passed_time":0.1321015588,"remaining_time":0.0969762888},
{"learn":[3712.815941],"iteration":173,"passed_time":0.1328788582,"remaining_time":0.09622262146},
{"learn":[3705.346096],"iteration":174,"passed_time":0.1336375777,"remaining_time":0.09545541263},
{"learn":[3700.777173],"iteration":175,"passed_time":0.1343794809,"remaining_time":0.09467645244},
{"learn":[3697.300384],"iteration":176,"passed_time":0.1351653971,"remaining_time":0.09392849632},
{"learn":[3694.732218],"iteration":177,"passed_time":0.1360374157,"remaining_time":0.09323912759},
{"learn":[3691.79182],"iteration":178,"passed_time":0.1367920815,"remaining_time":0.09246839032},
{"learn":[3688.353543],"iteration":179,"passed_time":0.1375348608,"remaining_time":0.09168990717},
{"learn":[3687.383686],"iteration":180,"passed_time":0.1380232118,"remaining_time":0.09074454259},
{"learn":[3682.446551],"iteration":181,"passed_time":0.1387768134,"remaining_time":0.08997617569},
{"learn":[3679.748919],"iteration":182,"passed_time":0.1396046208,"remaining_time":0.08925541332},
{"learn":[3675.617828],"iteration":183,"passed_time":0.1403987025,"remaining_time":0.08851222546},
{"learn":[3671.840244],"iteration":184,"passed_time":0.1411672112,"remaining_time":0.08775259075},
{"learn":[3670.075173],"iteration":185,"passed_time":0.1419139352,"remaining_time":0.08697950867},
{"learn":[3666.211547],"iteration":186,"passed_time":0.1426755086,"remaining_time":0.08621568165},
{"learn":[3661.916315],"iteration":187,"passed_time":0.1434260964,"remaining_time":0.08544533404},
{"learn":[3660.129086],"iteration":188,"passed_time":0.1441896356,"remaining_time":0.08468280188},
{"learn":[3657.280359],"iteration":189,"passed_time":0.144987922,"remaining_time":0.08394037591},
{"learn":[3652.63946],"iteration":190,"passed_time":0.1457542628,"remaining_time":0.08317913427},
{"learn":[3650.248549],"iteration":191,"passed_time":0.1465717066,"remaining_time":0.08244658498},
{"learn":[3646.854248],"iteration":192,"passed_time":0.1473253405,"remaining_time":0.08167777946},
{"learn":[3643.87225],"iteration":193,"passed_time":0.1481216511,"remaining_time":0.08093244852},
{"learn":[3639.548417],"iteration":194,"passed_time":0.1488802156,"remaining_time":0.08016626993},
{"learn":[3635.061669],"iteration":195,"passed_time":0.1496452479,"remaining_time":0.07940360091},
{"learn":[3631.743638],"iteration":196,"passed_time":0.1504217047,"remaining_time":0.07864688115},
{"learn":[3628.889039],"iteration":197,"passed_time":0.1511977752,"remaining_time":0.07788976299},
{"learn":[3622.921039],"iteration":198,"passed_time":0.1520910895,"remaining_time":0.07719196002},
{"learn":[3621.556548],"iteration":199,"passed_time":0.1529391498,"remaining_time":0.07646957491},
{"learn":[3618.601232],"iteration":200,"passed_time":0.1538126432,"remaining_time":0.07575846603},
{"learn":[3614.948006],"iteration":201,"passed_time":0.1545899753,"remaining_time":0.07499909694},
{"learn":[3612.896653],"iteration":202,"passed_time":0.1553737625,"remaining_time":0.07424263529},
{"learn":[3611.210189],"iteration":203,"passed_time":0.1561147456,"remaining_time":0.07346576265},
{"learn":[3611.057272],"iteration":204,"passed_time":0.1563324422,"remaining_time":0.07244674149},
{"learn":[3608.102311],"iteration":205,"passed_time":0.1570991211,"remaining_time":0.07168600671},
{"learn":[3606.426922],"iteration":206,"passed_time":0.1578435979,"remaining_time":0.07091523964},
{"learn":[3603.018832],"iteration":207,"passed_time":0.1586040518,"remaining_time":0.07015179215},
{"learn":[3594.278775],"iteration":208,"passed_time":0.1593850309,"remaining_time":0.06939731011},
{"learn":[3593.671843],"iteration":209,"passed_time":0.1601208799,"remaining_time":0.06862323425},
{"learn":[3590.572834],"iteration":210,"passed_time":0.1608925094,"remaining_time":0.06786461298},
{"learn":[3587.258741],"iteration":211,"passed_time":0.1616504968,"remaining_time":0.06710020623},
{"learn":[3585.615928],"iteration":212,"passed_time":0.1624577571,"remaining_time":0.06635598529},
{"learn":[3579.839946],"iteration":213,"passed_time":0.163645178,"remaining_time":0.06576395005},
{"learn":[3577.937535],"iteration":214,"passed_time":0.1644740292,"remaining_time":0.0650246162},
{"learn":[3572.454772],"iteration":215,"passed_time":0.165262497,"remaining_time":0.06426874885},
{"learn":[3571.519257],"iteration":216,"passed_time":0.1660908024,"remaining_time":0.06352781844},
{"learn":[3568.415433],"iteration":217,"passed_time":0.166893714,"remaining_time":0.06277653463},
{"learn":[3566.567958],"iteration":218,"passed_time":0.1676846129,"remaining_time":0.06202033628},
{"learn":[3563.63615],"iteration":219,"passed_time":0.1684885127,"remaining_time":0.06126855009},
{"learn":[3558.877568],"iteration":220,"passed_time":0.1692925028,"remaining_time":0.06051632453},
{"learn":[3554.337759],"iteration":221,"passed_time":0.1700686125,"remaining_time":0.05975383684},
{"learn":[3552.473433],"iteration":222,"passed_time":0.1708267979,"remaining_time":0.05898503785},
{"learn":[3552.125456],"iteration":223,"passed_time":0.171196011,"remaining_time":0.05808436086},
{"learn":[3549.542318],"iteration":224,"passed_time":0.1719355351,"remaining_time":0.05731184504},
{"learn":[3546.519413],"iteration":225,"passed_time":0.1726938558,"remaining_time":0.0565457758},
{"learn":[3543.594421],"iteration":226,"passed_time":0.1734436524,"remaining_time":0.05577703359},
{"learn":[3542.255258],"iteration":227,"passed_time":0.1742348095,"remaining_time":0.0550215188},
{"learn":[3536.87552],"iteration":228,"passed_time":0.1750929666,"remaining_time":0.05428646562},
{"learn":[3534.012253],"iteration":229,"passed_time":0.1759566197,"remaining_time":0.05355201468},
{"learn":[3533.20608],"iteration":230,"passed_time":0.1767784649,"remaining_time":0.05280395704},
{"learn":[3530.424441],"iteration":231,"passed_time":0.1776522881,"remaining_time":0.05207049823},
{"learn":[3527.191489],"iteration":232,"passed_time":0.1790015227,"remaining_time":0.05147254086},
{"learn":[3524.525638],"iteration":233,"passed_time":0.1799210249,"remaining_time":0.05074695574},
{"learn":[3520.530626],"iteration":234,"passed_time":0.1808069786,"remaining_time":0.05001044088},
{"learn":[3514.884344],"iteration":235,"passed_time":0.1817145473,"remaining_time":0.04927852129},
{"learn":[3513.571987],"iteration":236,"passed_time":0.1826652472,"remaining_time":0.04855658469},
{"learn":[3510.888606],"iteration":237,"passed_time":0.1838969146,"remaining_time":0.04790591893},
{"learn":[3509.184033],"iteration":238,"passed_time":0.1850224037,"remaining_time":0.04722329131},
{"learn":[3505.775501],"iteration":239,"passed_time":0.1860649711,"remaining_time":0.04651624278},
{"learn":[3502.701372],"iteration":240,"passed_time":0.1870062099,"remaining_time":0.04578160325},
{"learn":[3501.059665],"iteration":241,"passed_time":0.1878623728,"remaining_time":0.04502486622},
{"learn":[3495.198056],"iteration":242,"passed_time":0.1887902332,"remaining_time":0.04428412878},
{"learn":[3490.333045],"iteration":243,"passed_time":0.189711703,"remaining_time":0.04354039085},
{"learn":[3487.830019],"iteration":244,"passed_time":0.1906897966,"remaining_time":0.04280791353},
{"learn":[3485.255457],"iteration":245,"passed_time":0.1915322249,"remaining_time":0.04204365911},
{"learn":[3480.180695],"iteration":246,"passed_time":0.1922800008,"remaining_time":0.04125846171},
{"learn":[3477.729685],"iteration":247,"passed_time":0.1930466666,"remaining_time":0.04047752688},
{"learn":[3474.701681],"iteration":248,"passed_time":0.1938204738,"remaining_time":0.03969816933},
{"learn":[3473.163358],"iteration":249,"passed_time":0.194577789,"remaining_time":0.03891555781},
{"learn":[3470.649423],"iteration":250,"passed_time":0.1953255812,"remaining_time":0.03813128875},
{"learn":[3464.581965],"iteration":251,"passed_time":0.1961214072,"remaining_time":0.03735645852},
{"learn":[3462.637095],"iteration":252,"passed_time":0.1970839025,"remaining_time":0.03661242458},
{"learn":[3458.966414],"iteration":253,"passed_time":0.1980377215,"remaining_time":0.03586509916},
{"learn":[3455.733646],"iteration":254,"passed_time":0.1989808011,"remaining_time":0.03511425901},
{"learn":[3452.663899],"iteration":255,"passed_time":0.1999588885,"remaining_time":0.03436793396},
{"learn":[3451.949716],"iteration":256,"passed_time":0.2011436797,"remaining_time":0.03365438999},
{"learn":[3449.897622],"iteration":257,"passed_time":0.2021287149,"remaining_time":0.03290467452},
{"learn":[3447.508717],"iteration":258,"passed_time":0.2030754136,"remaining_time":0.03214707319},
{"learn":[3444.632066],"iteration":259,"passed_time":0.2040003949,"remaining_time":0.03138467614},
{"learn":[3440.119486],"iteration":260,"passed_time":0.2048222818,"remaining_time":0.03060562831},
{"learn":[3435.77168],"iteration":261,"passed_time":0.2056152774,"remaining_time":0.02982206313},
{"learn":[3433.273954],"iteration":262,"passed_time":0.2064260361,"remaining_time":0.02904092524},
{"learn":[3431.045126],"iteration":263,"passed_time":0.2072071709,"remaining_time":0.0282555233},
{"learn":[3427.299959],"iteration":264,"passed_time":0.2079662426,"remaining_time":0.02746723959},
{"learn":[3423.145792],"iteration":265,"passed_time":0.2087229397,"remaining_time":0.026678872},
{"learn":[3421.250331],"iteration":266,"passed_time":0.2094468456,"remaining_time":0.02588668878},
{"learn":[3416.986003],"iteration":267,"passed_time":0.2102396466,"remaining_time":0.02510324139},
{"learn":[3411.712396],"iteration":268,"passed_time":0.2110213967,"remaining_time":0.02431845092},
{"learn":[3411.195523],"iteration":269,"passed_time":0.2117513636,"remaining_time":0.02352792929},
{"learn":[3408.256419],"iteration":270,"passed_time":0.2125664243,"remaining_time":0.02274696053},
{"learn":[3405.907403],"iteration":271,"passed_time":0.213405116,"remaining_time":0.02196817371},
{"learn":[3403.040502],"iteration":272,"passed_time":0.2142390573,"remaining_time":0.02118847819},
{"learn":[3402.417736],"iteration":273,"passed_time":0.2150745067,"remaining_time":0.02040852983},
{"learn":[3398.707964],"iteration":274,"passed_time":0.2158531767,"remaining_time":0.01962301606},
{"learn":[3393.724982],"iteration":275,"passed_time":0.216647188,"remaining_time":0.01883888592},
{"learn":[3388.443107],"iteration":276,"passed_time":0.2174334328,"remaining_time":0.01805403955},
{"learn":[3386.861867],"iteration":277,"passed_time":0.2182627154,"remaining_time":0.01727258899},
{"learn":[3382.551581],"iteration":278,"passed_time":0.2190279557,"remaining_time":0.01648597516},
{"learn":[3379.558924],"iteration":279,"passed_time":0.219806544,"remaining_time":0.01570046743},
{"learn":[3377.703195],"iteration":280,"passed_time":0.2205946193,"remaining_time":0.01491565042},
{"learn":[3373.975193],"iteration":281,"passed_time":0.2213601788,"remaining_time":0.01412937311},
{"learn":[3370.825741],"iteration":282,"passed_time":0.222146584,"remaining_time":0.01334449444},
{"learn":[3367.193402],"iteration":283,"passed_time":0.2228942873,"remaining_time":0.01255742464},
{"learn":[3363.073759],"iteration":284,"passed_time":0.2236945678,"remaining_time":0.0117733983},
{"learn":[3361.693986],"iteration":285,"passed_time":0.2244714333,"remaining_time":0.01098811212},
{"learn":[3360.702633],"iteration":286,"passed_time":0.2252328621,"remaining_time":0.01020218539},
{"learn":[3357.23852],"iteration":287,"passed_time":0.226025713,"remaining_time":0.009417738043},
{"learn":[3354.992703],"iteration":288,"passed_time":0.2268592917,"remaining_time":0.008634782728},
{"learn":[3351.699179],"iteration":289,"passed_time":0.2278731211,"remaining_time":0.00785769383},
{"learn":[3350.689967],"iteration":290,"passed_time":0.2287788489,"remaining_time":0.007075634503},
{"learn":[3349.01749],"iteration":291,"passed_time":0.2298958227,"remaining_time":0.006298515692},
{"learn":[3347.203474],"iteration":292,"passed_time":0.2308764263,"remaining_time":0.005515819058},
{"learn":[3343.92893],"iteration":293,"passed_time":0.2320995926,"remaining_time":0.00473672638},
{"learn":[3340.692836],"iteration":294,"passed_time":0.2335089958,"remaining_time":0.00395777959},
{"learn":[3338.830257],"iteration":295,"passed_time":0.2346488635,"remaining_time":0.003170930588},
{"learn":[3334.598531],"iteration":296,"passed_time":0.2357530516,"remaining_time":0.002381343955},
{"learn":[3332.216881],"iteration":297,"passed_time":0.2366771872,"remaining_time":0.001588437498},
{"learn":[3326.657385],"iteration":298,"passed_time":0.2375583948,"remaining_time":0.0007945096818},
{"learn":[3324.659643],"iteration":299,"passed_time":0.2384771119,"remaining_time":0}
]}